simple_pypackage/__init__.py
simple_pypackage-0.1.0.dist-info/LICENSE
simple_pypackage-0.1.0.dist-info/METADATA
simple_pypackage-0.1.0.dist-info/WHEEL
simple_pypackage-0.1.0.dist-info/top_level.txt
simple_pypackage-0.1.0.dist-info/RECORD
