Metadata-Version: 2.1
Name: simple-pypackage
Version: 0.1.0
Summary: A clean, automated setup for publishing simple Python packages to PyPI and Anaconda.
Home-page: https://github.com/ppeetteerrs/simple-pypackage
Author: Peter Yuen
Author-email: ppeetteerrsx@gmail.com
License: MIT license
Keywords: simple-pypackage
Platform: UNKNOWN
Requires-Python: >=3.8
